hhcp/__init__.py
hhcp/cp_dir_multi.py
hhcp/cp_list_multi.py
hhcp/version.py
hhcp/utils/__init__.py
hhcp/utils/chunks.py
tools/__init__.py
tools/hhcpsdk.py
hhcp-0.1.2.dist-info/METADATA
hhcp-0.1.2.dist-info/WHEEL
hhcp-0.1.2.dist-info/entry_points.txt
hhcp-0.1.2.dist-info/top_level.txt
hhcp-0.1.2.dist-info/RECORD
