Metadata-Version: 2.1
Name: hhcp
Version: 0.1.2
Summary: UNKNOWN
Home-page: UNKNOWN
License: UNKNOWN
Platform: UNKNOWN
